kicad_circuit_analysis/__init__.py
kicad_circuit_analysis/cli.py
kicad_circuit_analysis/py.typed
kicad_circuit_analysis/core/__init__.py
kicad_circuit_analysis/core/circuit_parser.py
kicad_circuit_analysis/fmea/__init__.py
kicad_circuit_analysis/fmea/comprehensive_fmea_report_generator.py
kicad_circuit_analysis/fmea/enhanced_fmea_analyzer.py
kicad_circuit_analysis/fmea/fmea_analyzer.py
kicad_circuit_analysis/fmea/fmea_report_generator.py
kicad_circuit_analysis/fmea/simple_fmea.py
kicad_circuit_analysis/mcp/__init__.py
kicad_circuit_analysis/mcp/server.py
kicad_circuit_analysis-0.0.1.dist-info/METADATA
kicad_circuit_analysis-0.0.1.dist-info/WHEEL
kicad_circuit_analysis-0.0.1.dist-info/entry_points.txt
kicad_circuit_analysis-0.0.1.dist-info/licenses/LICENSE
kicad_circuit_analysis-0.0.1.dist-info/RECORD
