Metadata-Version: 2.4
Name: kicad-circuit-analysis
Version: 0.0.1
Summary: Professional Circuit Quality Assurance and FMEA Analysis for KiCAD
Project-URL: Homepage, https://github.com/circuit-synth/kicad-circuit-analysis
Project-URL: Documentation, https://kicad-circuit-analysis.readthedocs.io
Project-URL: Repository, https://github.com/circuit-synth/kicad-circuit-analysis
Project-URL: Issues, https://github.com/circuit-synth/kicad-circuit-analysis/issues
Author-email: Circuit-Synth Team <contact@circuit-synth.com>
License-Expression: MIT
License-File: LICENSE
Keywords: ai-analysis,circuit-analysis,eda,electronics,fmea,kicad,quality-assurance,risk-assessment
Classifier: Development Status :: 3 - Alpha
Classifier: Intended Audience :: Developers
Classifier: Intended Audience :: Science/Research
Classifier: License :: OSI Approved :: MIT License
Classifier: Operating System :: OS Independent
Classifier: Programming Language :: Python :: 3
Classifier: Programming Language :: Python :: 3.10
Classifier: Programming Language :: Python :: 3.11
Classifier: Programming Language :: Python :: 3.12
Classifier: Topic :: Scientific/Engineering :: Electronic Design Automation (EDA)
Classifier: Topic :: Software Development :: Libraries :: Python Modules
Requires-Python: >=3.10
Requires-Dist: kicad-pcb-api>=0.0.1
Requires-Dist: kicad-sch-api>=0.0.1
Requires-Dist: loguru>=0.7.0
Requires-Dist: numpy>=1.24.0
Requires-Dist: pandas>=2.0.0
Provides-Extra: ai
Requires-Dist: anthropic>=0.8.0; extra == 'ai'
Requires-Dist: openai>=1.0.0; extra == 'ai'
Provides-Extra: dev
Requires-Dist: black>=23.0.0; extra == 'dev'
Requires-Dist: mypy>=1.7.0; extra == 'dev'
Requires-Dist: pytest-cov>=4.0.0; extra == 'dev'
Requires-Dist: pytest>=7.0.0; extra == 'dev'
Requires-Dist: ruff>=0.1.0; extra == 'dev'
Provides-Extra: mcp
Requires-Dist: mcp>=1.0.0; extra == 'mcp'
Provides-Extra: reporting
Requires-Dist: matplotlib>=3.7.0; extra == 'reporting'
Requires-Dist: openpyxl>=3.1.0; extra == 'reporting'
Requires-Dist: reportlab>=4.0.0; extra == 'reporting'
